appenginetaskutils-0.4.3.dist-info/DESCRIPTION.rst
appenginetaskutils-0.4.3.dist-info/METADATA
appenginetaskutils-0.4.3.dist-info/RECORD
appenginetaskutils-0.4.3.dist-info/WHEEL
appenginetaskutils-0.4.3.dist-info/metadata.json
appenginetaskutils-0.4.3.dist-info/top_level.txt
taskutils/__init__.py
taskutils/debouncedtask.py
taskutils/flash.py
taskutils/flaskutil.py
taskutils/future.py
taskutils/gcscacher.py
taskutils/gcsfilesharded.py
taskutils/memcacher.py
taskutils/ndbsharded.py
taskutils/splitutils.py
taskutils/task.py
taskutils/util.py
