Metadata-Version: 2.0
Name: appenginetaskutils
Version: 0.4.3
Summary: Utilities for using appengine tasks. Inspired by deferred.
Home-page: https://github.com/emlynoregan/appenginetaskutils
Author: Emlyn O'Regan
Author-email: emlynoregan@gmail.com
License: LICENSE.txt
Platform: UNKNOWN
Classifier: Development Status :: 3 - Alpha
Classifier: Intended Audience :: Developers
Classifier: License :: OSI Approved :: Apache Software License
Classifier: Operating System :: POSIX
Classifier: Operating System :: Microsoft :: Windows
Classifier: Operating System :: MacOS :: MacOS X
Classifier: Programming Language :: Python :: 2.7
Classifier: Programming Language :: Python :: Implementation :: CPython
Classifier: Topic :: Software Development :: Libraries :: Python Modules
Classifier: Topic :: System :: Distributed Computing
Requires-Dist: GoogleAppEngineCloudStorageClient
Requires-Dist: Werkzeug (==0.12.2)
Requires-Dist: cloudpickle
Requires-Dist: google-cloud-storage
